test_utils/__init__.py
test_utils/imports.py
test_utils/orchestrate.py
test_utils/prefixer.py
test_utils/py.typed
test_utils/retry.py
test_utils/system.py
test_utils/version.py
test_utils/vpcsc_config.py
test_utils/lower_bound_checker/__init__.py
test_utils/lower_bound_checker/lower_bound_checker.py
google_cloud_testutils-1.6.2.dist-info/LICENSE
google_cloud_testutils-1.6.2.dist-info/METADATA
google_cloud_testutils-1.6.2.dist-info/WHEEL
google_cloud_testutils-1.6.2.dist-info/entry_points.txt
google_cloud_testutils-1.6.2.dist-info/top_level.txt
google_cloud_testutils-1.6.2.dist-info/RECORD
